[
  {
    "Root": "C:\\Users\\admin\\Desktop\\Nova estrutura de scripts",
    "Inputs": [
      {
        "Type": "Text",
        "Value": "--FILE AMALGAMATION",
        "SubFolder": null,
        "Recursive": true,
        "Encoding": null,
        "Expressions": []
      },
      {
        "Type": "FileSearchExpressionFilter",
        "Value": "*.sql",
        "SubFolder": "3.9",
        "Recursive": true,
        "Encoding": null,
        "Expressions": []
      }
    ],
    "Outputs": [
      {
        "SubFolder": "OUT",
        "FileName": "2.8.3_3.9.sql",
        "Encoding": null
      }
    ],
    "Separator": "\r\n--SEPARATOR--\r\n"
  }
]